MANIFEST.in
README.txt
setup.py
XStatic_tv4.egg-info/PKG-INFO
XStatic_tv4.egg-info/SOURCES.txt
XStatic_tv4.egg-info/dependency_links.txt
XStatic_tv4.egg-info/namespace_packages.txt
XStatic_tv4.egg-info/not-zip-safe
XStatic_tv4.egg-info/top_level.txt
xstatic/__init__.py
xstatic/pkg/__init__.py
xstatic/pkg/tv4/__init__.py
xstatic/pkg/tv4/data/tv4.async-jquery.js
xstatic/pkg/tv4/data/tv4.js
xstatic/pkg/tv4/data/tv4.min.js