Metadata-Version: 1.0
Name: XStatic-tv4
Version: 1.2.7.0
Summary: tv4 1.2.7 (XStatic packaging standard)
Home-page: http://geraintluff.github.com/tv4/
Author: Rob Cresswell
Author-email: robert.cresswell@outlook.com
License: https://github.com/geraintluff/tv4/blob/master/LICENSE.txt
Keywords: tv4 xstatic
Platform: any
